{"Most popular":[{"keyName":"Create a new page (desktop only)","keyTrans":"创建新页面（仅限桌面）","keyValue":"CTRL N"},{"keyName":"Open a new Notion window","keyTrans":"打开新的 Notion 窗口","keyValue":"CTRL ⇧ N"},{"keyName":"Open search","keyTrans":"打开搜索","keyValue":"CTRL P"},{"keyName":"Go back","keyTrans":"后退","keyValue":"CTRL ["},{"keyName":"Go forward","keyTrans":"前进","keyValue":"CTRL ]"},{"keyName":"Switch dark mode / light mode","keyTrans":"切换深色模式/浅色模式","keyValue":"CTRL ⇧ L"}],"Markdown":[{"keyName":"Bold","keyTrans":"粗体","keyValue":"** on either side"},{"keyName":"Italicize","keyTrans":"斜体","keyValue":"* or _ on either side"},{"keyName":"Inline code","keyTrans":"内联代码","keyValue":"` on either side"},{"keyName":"Strikethrough","keyTrans":"删除线","keyValue":"~ on either side"},{"keyName":"Bullet list","keyTrans":"弹出列表","keyValue":"- "},{"keyName":"Checkbox","keyTrans":"复选框","keyValue":"[]"},{"keyName":"Numbered list","keyTrans":"编号列表","keyValue":"1."},{"keyName":"H1","keyTrans":"H1","keyValue":"#"},{"keyName":"H2","keyTrans":"H2","keyValue":"##"},{"keyName":"H3","keyTrans":"H3","keyValue":"###"},{"keyName":"Toggle list","keyTrans":"切换列表","keyValue":">"},{"keyName":"Quote block","keyTrans":"引用块","keyValue":"“"}],"Create and style your content":[{"keyName":"Insert a line of text","keyTrans":"插入一行文本","keyValue":"↩ "},{"keyName":"Create a line break within a block of text","keyTrans":"在文本块内创建换行符","keyValue":"⇧ ↩"},{"keyName":"Create a comment","keyTrans":"创建注释","keyValue":"CTRL ⇧ M"},{"keyName":"Divider","keyTrans":"分隔线","keyValue":"---"},{"keyName":"Bold (when text selected)","keyTrans":"粗体（选中文本时）","keyValue":"CTRL B"},{"keyName":"Italicize (when text selected)","keyTrans":"斜体（选中文本时）","keyValue":"CTRL I"},{"keyName":"Underline (when text selected)","keyTrans":"下划线（选中文本时）","keyValue":"CTRL U"},{"keyName":"Strikethrough (when text selected)","keyTrans":"删除线（选中文本时）","keyValue":"CTRL ⇧ S"},{"keyName":"Add a link (when text selected)","keyTrans":"添加链接（选中文本时）","keyValue":"CTRL K"},{"keyName":"Paste over a link (when text selected)","keyTrans":"在链接上粘贴（选中文本时）","keyValue":"CTRL V"},{"keyName":"Inline code (when text selected)","keyTrans":"内联代码（选中文本时）","keyValue":"CTRL E"},{"keyName":"Indent / nest content","keyTrans":"缩进/嵌套内容","keyValue":"Tab"},{"keyName":"Un-indent / Un-nest content","keyTrans":"取消缩进/嵌套内容","keyValue":"⇧ Tab"},{"keyName":"Turn something in a different block-type","keyTrans":"将内容转为不同的块类型","keyValue":"Type /turn"},{"keyName":"Change color or highlight color","keyTrans":"更改颜色或高亮颜色","keyValue":"Type /color"},{"keyName":"Reset color or highlight color","keyTrans":"重置颜色或高亮颜色","keyValue":"Type /default"}],"Edit and move blocks":[{"keyName":"Select block you’re currently in","keyTrans":"选择当前所在的块","keyValue":"Esc"},{"keyName":"Select the block your cursor is in","keyTrans":"选择光标所在的区块","keyValue":"CTRL A"},{"keyName":"Open selected image fullscreen","keyTrans":"全屏打开所选图片","keyValue":"Space"},{"keyName":"Select a different block","keyTrans":"选择不同的图块","keyValue":"↑ → ↓ ←"},{"keyName":"Expand your selection","keyTrans":"扩展您的选择","keyValue":"⇧ ↑ → ↓ ←"},{"keyName":"Select an entire block","keyTrans":"选择整个图块","keyValue":"CTRL ⇧ Click"},{"keyName":"Select another block and all blocks in between","keyTrans":"选择另一个图块和中间的所有图块","keyValue":"⇧ Click"},{"keyName":"Delete selected blocks","keyTrans":"删除所选图块","keyValue":"Backspace or Delete"},{"keyName":"Duplicate the block(s) you’ve selected","keyTrans":"复制所选图块","keyValue":"CTRL D"},{"keyName":"Edit any text inside a selected block","keyTrans":"编辑所选区块内的任何文本","keyValue":"↩ "},{"keyName":"Open a page inside a page","keyTrans":"在页面内打开页面","keyValue":"↩ "},{"keyName":"Select multiple cards to edit them all at once (board view)","keyTrans":"选择多个图块，同时对它们进行编辑（棋盘视图）","keyValue":"CTRL /"},{"keyName":"Move a selected block around","keyTrans":"移动选中的图块","keyValue":"CTRL ⇧ ↑ → ↓ ←"},{"keyName":"Expand or close all toggles in a toggle list","keyTrans":"展开或关闭切换列表中的所有切换按钮","keyValue":"CTRL ⌥ T"},{"keyName":"Apply the last color or highlight color you used","keyTrans":"应用上次使用的颜色或高亮颜色","keyValue":"CTRL ⇧ H"},{"keyName":"Modify the current block you’re in","keyTrans":"修改当前所在的区块","keyValue":"CTRL ↩ "},{"keyName":"Mention a person / page / date","keyTrans":"提及某个人/页面/日期","keyValue":"@"},{"keyName":"Add a reminder","keyTrans":"添加提醒","keyValue":"@remind (following by a date)"},{"keyName":"Dismiss @-menu","keyTrans":"取消 @ 菜单","keyValue":"Esc"},{"keyName":"Create a sub-page, page somewhere else or link a page","keyTrans":"创建子页面、其他页面或链接页面","keyValue":"+ or [["},{"keyName":"Move page to","keyTrans":"将页面移至","keyValue":"CTRL ⇧ P"}],"/Slash commands":[{"keyName":"Create a new text block","keyTrans":"创建新文本块","keyValue":"/text or /plain"},{"keyName":"Create a new page","keyTrans":"创建新页面","keyValue":"/page"},{"keyName":"Create a bullet list","keyTrans":"创建项目列表","keyValue":"/bullet"},{"keyName":"Create a numbered list","keyTrans":"创建编号列表","keyValue":"/num"},{"keyName":"Create a todo list with checkboxes","keyTrans":"创建带复选框的待办事项列表","keyValue":"/todo"},{"keyName":"Create a toggle list","keyTrans":"创建切换列表","keyValue":"/toggle"},{"keyName":"Create a light gray divider","keyTrans":"创建浅灰色分隔线","keyValue":"/div"},{"keyName":"Create a quote block","keyTrans":"创建引用块","keyValue":"/quote"},{"keyName":"Create a h1","keyTrans":"创建 h1","keyValue":"/h1 or /#"},{"keyName":"Create a h2","keyTrans":"创建 h2","keyValue":"/h2 or /##"},{"keyName":"Create a h3","keyTrans":"创建 h3","keyValue":"/h3 or /###"},{"keyName":"Create a link to another page","keyTrans":"创建指向其他页面的链接","keyValue":"/link"},{"keyName":"Clears the / menu when writing a /","keyTrans":"编写 / 时清除 / 菜单","keyValue":"Esc"},{"keyName":"Mention. ","keyTrans":"提及","keyValue":"/mention"},{"keyName":"Add a timestamp or reminder","keyTrans":"添加时间戳或提醒","keyValue":"/date or /reminder"},{"keyName":"TeX formula","keyTrans":"TeX 公式","keyValue":"/equation"},{"keyName":"Show emoji picker","keyTrans":"显示表情符号选择器","keyValue":"/emoji"},{"keyName":"Create a table","keyTrans":"创建表格","keyValue":"/table-full or /table-inline"},{"keyName":"Create a Kanban board","keyTrans":"创建看板","keyValue":"/board-full or /board-inline"},{"keyName":"Create a calendar","keyTrans":"创建日历","keyValue":"/calendar-full or /calendar-inline"},{"keyName":"Create a list database","keyTrans":"创建列表数据库","keyValue":"/list-full or /list-inline"},{"keyName":"Create a gallery","keyTrans":"创建图库","keyValue":"/gallery-full or /gallery-inline"},{"keyName":"Create a timeline or gantt chart","keyTrans":"创建时间轴或甘特图","keyValue":"/timeline-full or /timeline-inline"},{"keyName":"Create a linked database","keyTrans":"创建链接数据库","keyValue":"/linked"},{"keyName":"Upload or embed image","keyTrans":"上传或嵌入图片","keyValue":"/image"},{"keyName":"Upload a PDF","keyTrans":"上传 PDF","keyValue":"/pdf"},{"keyName":"Add a bookmark","keyTrans":"添加书签","keyValue":"/book"},{"keyName":"Upload or embed video","keyTrans":"上传或嵌入视频","keyValue":"/video"},{"keyName":"Upload or embed audio","keyTrans":"上传或嵌入音频","keyValue":"/audio"},{"keyName":"Create a code block","keyTrans":"创建代码块","keyValue":"/code"},{"keyName":"Upload any file","keyTrans":"上传任何文件","keyValue":"/file"},{"keyName":"Embed anything","keyTrans":"嵌入任何内容","keyValue":"/embed"},{"keyName":"Comment on any block","keyTrans":"评论任何区块","keyValue":"/comment"},{"keyName":"Duplicate the current block","keyTrans":"复制当前区块","keyValue":"/duplicate"},{"keyName":"Move a block to another page","keyTrans":"将代码块移至其他页面","keyValue":"/moveto"},{"keyName":"Delete the current block","keyTrans":"删除当前区块","keyValue":"/delete"},{"keyName":"Create a table of contents","keyTrans":"创建目录","keyValue":"/toc"},{"keyName":"Create a template button","keyTrans":"创建模板按钮","keyValue":"/button or /template"},{"keyName":"Create a breadcrumb button-group","keyTrans":"创建面包屑按钮组","keyValue":"/bread"},{"keyName":"Write mathematical equations and symbols","keyTrans":"书写数学公式和符号","keyValue":"/math or /latex"}],"toolTrans":["最受欢迎","标记符","创建和调整内容样式","编辑和移动区块","/Slash 命令"]}